{
    "total": {
        "potencia": 8.063,
        "energia_hoy": 2.34,
        "energia_total": 92386.97
    },
    "sebadal": {
        "potencia": 8.06,
        "ultima_produccion_valor": 8.063,
        "ultima_produccion_hora": "2026-02-07 09:00",
        "uso_total": 2270.35,
        "autoconsumo": 2.34,
        "compra_red": 99.93,
        "exportacion_red": 5.72,
        "bateria_kw": 0.0,
        "bateria_soc": 0.0,
        "ratio_autoconsumo": 0.2903,
        "ratio_autonomia": 0.001
    },
    "actualizado": "2026-02-07 09:01:08"
}