{
    "total": {
        "potencia": 19.91,
        "energia_hoy": 77.79,
        "energia_total": 91170.69
    },
    "sebadal": {
        "potencia": 19.91,
        "ultima_produccion_valor": 19.91,
        "ultima_produccion_hora": "2026-02-02 14:00",
        "uso_total": 279.43,
        "autoconsumo": 70.6,
        "compra_red": 75.43,
        "exportacion_red": 0.0,
        "bateria_kw": 0.0,
        "bateria_soc": 0.0,
        "ratio_autoconsumo": 1.0,
        "ratio_autonomia": 0.2527
    },
    "actualizado": "2026-02-02 14:03:54"
}